timee/__init__.py
timee/cli.py
timee/timee_core.py
timee/timee_dt.py
timee/timee_duration.py
timee/timee_general.py
timee-0.1.1.dist-info/DESCRIPTION.rst
timee-0.1.1.dist-info/METADATA
timee-0.1.1.dist-info/RECORD
timee-0.1.1.dist-info/WHEEL
timee-0.1.1.dist-info/entry_points.txt
timee-0.1.1.dist-info/metadata.json
timee-0.1.1.dist-info/top_level.txt
