Metadata-Version: 2.0
Name: timee
Version: 0.1.1
Summary: Datetime library
Home-page: https://github.com/eyalev/timee
Author: Eyal Levin
Author-email: eyalev@gmail.com
License: MIT license
Keywords: timee
Platform: UNKNOWN
Classifier: Development Status :: 2 - Pre-Alpha
Classifier: Intended Audience :: Developers
Classifier: License :: OSI Approved :: MIT License
Classifier: Natural Language :: English
Classifier: Programming Language :: Python :: 2
Classifier: Programming Language :: Python :: 2.6
Classifier: Programming Language :: Python :: 2.7
Classifier: Programming Language :: Python :: 3
Classifier: Programming Language :: Python :: 3.3
Classifier: Programming Language :: Python :: 3.4
Classifier: Programming Language :: Python :: 3.5
Requires-Dist: click (==6.7)
Requires-Dist: maya (==0.3.2)
Requires-Dist: pytimeparse (==1.1.6)
